dialogue_guardian-1.3.0.dist-info/licenses/LICENSE
guardian/__init__.py
guardian/cli.py
guardian/core.py
dialogue_guardian-1.3.0.dist-info/METADATA
dialogue_guardian-1.3.0.dist-info/WHEEL
dialogue_guardian-1.3.0.dist-info/entry_points.txt
dialogue_guardian-1.3.0.dist-info/top_level.txt
dialogue_guardian-1.3.0.dist-info/RECORD
