Metadata-Version: 2.4
Name: dialogue-guardian
Version: 1.3.0
Summary: Universal Media Censor - Automatically detect and censor profane language in video files
Home-page: https://github.com/tsnearly/dialogue-guardian
Author: Tony Snearly
License: OSL-3.0
Project-URL: Homepage, https://github.com/tsnearly/dialogue-guardian
Project-URL: Documentation, https://tsnearly.github.io/dialogue-guardian/
Project-URL: Repository, https://github.com/tsnearly/dialogue-guardian.git
Project-URL: Issues, https://github.com/tsnearly/dialogue-guardian/issues
Project-URL: Changelog, https://tsnearly.github.io/dialogue-guardian/changelog.html
Keywords: video,audio,censoring,subtitles,ffmpeg,profanity,media
Classifier: Development Status :: 4 - Beta
Classifier: Intended Audience :: Developers
Classifier: Intended Audience :: End Users/Desktop
Classifier: Topic :: Multimedia :: Video
Classifier: Topic :: Text Processing :: Filters
Classifier: Programming Language :: Python :: 3
Classifier: Programming Language :: Python :: 3.8
Classifier: Programming Language :: Python :: 3.9
Classifier: Programming Language :: Python :: 3.10
Classifier: Programming Language :: Python :: 3.11
Classifier: Programming Language :: Python :: 3.12
Classifier: Operating System :: OS Independent
Requires-Python: >=3.7
License-File: LICENSE
Requires-Dist: srt
Dynamic: home-page
Dynamic: license-file
Dynamic: requires-python
